ssb_pypitest_osn/__init__.py
ssb_pypitest_osn/__main__.py
ssb_pypitest_osn/functions.py
ssb_pypitest_osn/py.typed
ssb_pypitest_osn-0.0.2.dist-info/LICENSE
ssb_pypitest_osn-0.0.2.dist-info/METADATA
ssb_pypitest_osn-0.0.2.dist-info/WHEEL
ssb_pypitest_osn-0.0.2.dist-info/entry_points.txt
ssb_pypitest_osn-0.0.2.dist-info/RECORD
